inaccel/tf_quant_finance/__init__.py
inaccel/tf_quant_finance/black_scholes/__init__.py
inaccel/tf_quant_finance/black_scholes/vanilla_prices.py
inaccel_tf_quant_finance-0.0.1.6.dist-info/LICENSE
inaccel_tf_quant_finance-0.0.1.6.dist-info/METADATA
inaccel_tf_quant_finance-0.0.1.6.dist-info/NOTICE
inaccel_tf_quant_finance-0.0.1.6.dist-info/WHEEL
inaccel_tf_quant_finance-0.0.1.6.dist-info/top_level.txt
inaccel_tf_quant_finance-0.0.1.6.dist-info/zip-safe
inaccel_tf_quant_finance-0.0.1.6.dist-info/RECORD
