Metadata-Version: 2.1
Name: inaccel-tf-quant-finance
Version: 0.0.1.6
Summary: InAccel tf-quant-finance-like package
Home-page: https://docs.inaccel.com
Author: InAccel
Author-email: info@inaccel.com
License: Apache-2.0
Keywords: InAccel Coral,FPGA,inaccel,tf-quant-finance
Classifier: Development Status :: 5 - Production/Stable
Classifier: License :: OSI Approved :: Apache Software License
Classifier: Operating System :: POSIX :: Linux
Classifier: Programming Language :: Python
Classifier: Programming Language :: Python :: 3
Classifier: Programming Language :: Python :: 3.8
Classifier: Programming Language :: Python :: 3.9
Classifier: Programming Language :: Python :: 3.10
Requires-Python: >=3.8
License-File: LICENSE
License-File: NOTICE
Requires-Dist: coral-api (==2.*)
Requires-Dist: tf-quant-finance (==0.0.1.dev26)
